pyodide_interrupts-0.1.1.dist-info/top_level.txt
pyodide_interrupts-0.1.1.dist-info/METADATA
pyodide_interrupts-0.1.1.dist-info/RECORD
pyodide_interrupts-0.1.1.dist-info/LICENSE
pyodide_interrupts-0.1.1.dist-info/WHEEL
pyodide_interrupts/__init__.py
pyodide_interrupts/_pyodide_interrupts.cpython-36m-x86_64-linux-gnu.so
