Metadata-Version: 2.1
Name: pyodide-interrupts
Version: 0.1.1
Summary: Interrupt handling for pyodide.
Home-page: https://github.com/SpectralSequences/pyodide_interrupts/
Author: Hood Chatham
Author-email: roberthoodchatham@gmail.com
License: UNKNOWN
Platform: UNKNOWN
Classifier: Programming Language :: Python :: 3
Classifier: License :: OSI Approved :: MIT License
Classifier: Operating System :: OS Independent
